ioe/__init__.py
ioe/ocpp/__init__.py
ioe/ocpp/client.py
ioe/ocpp/server.py
ioe/ocpp/OCPP-2.0_part3_schemas/AuthorizeRequest_v1p0.json
ioe/ocpp/OCPP-2.0_part3_schemas/AuthorizeResponse_v1p0.json
ioe/ocpp/OCPP-2.0_part3_schemas/BootNotificationRequest_v1p0.json
ioe/ocpp/OCPP-2.0_part3_schemas/BootNotificationResponse_v1p0.json
ioe/ocpp/OCPP-2.0_part3_schemas/CancelReservationRequest_v1p0.json
ioe/ocpp/OCPP-2.0_part3_schemas/CancelReservationResponse_v1p0.json
ioe/ocpp/OCPP-2.0_part3_schemas/CertificateSignedRequest_v1p0.json
ioe/ocpp/OCPP-2.0_part3_schemas/CertificateSignedResponse_v1p0.json
ioe/ocpp/OCPP-2.0_part3_schemas/ChangeAvailabilityRequest_v1p0.json
ioe/ocpp/OCPP-2.0_part3_schemas/ChangeAvailabilityResponse_v1p0.json
ioe/ocpp/OCPP-2.0_part3_schemas/ClearCacheRequest_v1p0.json
ioe/ocpp/OCPP-2.0_part3_schemas/ClearCacheResponse_v1p0.json
ioe/ocpp/OCPP-2.0_part3_schemas/ClearChargingProfileRequest_v1p0.json
ioe/ocpp/OCPP-2.0_part3_schemas/ClearChargingProfileResponse_v1p0.json
ioe/ocpp/OCPP-2.0_part3_schemas/ClearDisplayMessageRequest_v1p0.json
ioe/ocpp/OCPP-2.0_part3_schemas/ClearDisplayMessageResponse_v1p0.json
ioe/ocpp/OCPP-2.0_part3_schemas/ClearVariableMonitoringRequest_v1p0.json
ioe/ocpp/OCPP-2.0_part3_schemas/ClearVariableMonitoringResponse_v1p0.json
ioe/ocpp/OCPP-2.0_part3_schemas/ClearedChargingLimitRequest_v1p0.json
ioe/ocpp/OCPP-2.0_part3_schemas/ClearedChargingLimitResponse_v1p0.json
ioe/ocpp/OCPP-2.0_part3_schemas/CostUpdatedRequest_v1p0.json
ioe/ocpp/OCPP-2.0_part3_schemas/CostUpdatedResponse_v1p0.json
ioe/ocpp/OCPP-2.0_part3_schemas/CustomerInformationRequest_v1p0.json
ioe/ocpp/OCPP-2.0_part3_schemas/CustomerInformationResponse_v1p0.json
ioe/ocpp/OCPP-2.0_part3_schemas/DataTransferRequest_v1p0.json
ioe/ocpp/OCPP-2.0_part3_schemas/DataTransferResponse_v1p0.json
ioe/ocpp/OCPP-2.0_part3_schemas/DeleteCertificateRequest_v1p0.json
ioe/ocpp/OCPP-2.0_part3_schemas/DeleteCertificateResponse_v1p0.json
ioe-0.0.26.dist-info/METADATA
ioe-0.0.26.dist-info/RECORD
ioe-0.0.26.dist-info/WHEEL
ioe-0.0.26.dist-info/top_level.txt
