Metadata-Version: 2.1
Name: ioe
Version: 0.0.26
Summary: The Python Internet of Energy Library
Home-page: https://gitlab.com/sergioalonso/ioe
Author: Sergio Alonso
Author-email: sergio@sergioalonso.es
License: UNKNOWN
Platform: UNKNOWN
Classifier: Programming Language :: Python :: 3
Classifier: License :: Public Domain
Classifier: Operating System :: POSIX :: Linux
Requires-Dist: jsonschema
Requires-Dist: websockets
Requires-Dist: websocket-client
